{
  "meta": {
    "description": "OTIF mensile aggregato — On Time In Full calcolato su tutti gli ordini. Mese di riferimento = mese dell'ordine (OrderDate). Ordini non evasi contano come NOT on time e NOT in full.",
    "tables": [
      "Ordinato",
      "Venduto"
    ],
    "generated_at": "2026-02-24"
  },
  "data": [
    {
      "month": "2023-01",
      "total_orders": 2142,
      "otif_orders": 711,
      "on_time_orders": 784,
      "in_full_orders": 1860,
      "otif_rate": 0.3319,
      "on_time_rate": 0.366,
      "in_full_rate": 0.8683
    },
    {
      "month": "2023-02",
      "total_orders": 7825,
      "otif_orders": 2544,
      "on_time_orders": 2790,
      "in_full_orders": 6779,
      "otif_rate": 0.3251,
      "on_time_rate": 0.3565,
      "in_full_rate": 0.8663
    },
    {
      "month": "2023-03",
      "total_orders": 12285,
      "otif_orders": 4000,
      "on_time_orders": 4398,
      "in_full_orders": 10614,
      "otif_rate": 0.3256,
      "on_time_rate": 0.358,
      "in_full_rate": 0.864
    },
    {
      "month": "2023-04",
      "total_orders": 11880,
      "otif_orders": 3883,
      "on_time_orders": 4269,
      "in_full_orders": 10286,
      "otif_rate": 0.3269,
      "on_time_rate": 0.3593,
      "in_full_rate": 0.8658
    },
    {
      "month": "2023-05",
      "total_orders": 12300,
      "otif_orders": 4029,
      "on_time_orders": 4434,
      "in_full_orders": 10680,
      "otif_rate": 0.3276,
      "on_time_rate": 0.3605,
      "in_full_rate": 0.8683
    },
    {
      "month": "2023-06",
      "total_orders": 11973,
      "otif_orders": 3877,
      "on_time_orders": 4256,
      "in_full_orders": 10379,
      "otif_rate": 0.3238,
      "on_time_rate": 0.3555,
      "in_full_rate": 0.8669
    },
    {
      "month": "2023-07",
      "total_orders": 12026,
      "otif_orders": 3972,
      "on_time_orders": 4338,
      "in_full_orders": 10433,
      "otif_rate": 0.3303,
      "on_time_rate": 0.3607,
      "in_full_rate": 0.8675
    },
    {
      "month": "2023-08",
      "total_orders": 12040,
      "otif_orders": 4090,
      "on_time_orders": 4432,
      "in_full_orders": 10547,
      "otif_rate": 0.3397,
      "on_time_rate": 0.3681,
      "in_full_rate": 0.876
    },
    {
      "month": "2023-09",
      "total_orders": 11996,
      "otif_orders": 3904,
      "on_time_orders": 4248,
      "in_full_orders": 10412,
      "otif_rate": 0.3254,
      "on_time_rate": 0.3541,
      "in_full_rate": 0.868
    },
    {
      "month": "2023-10",
      "total_orders": 12263,
      "otif_orders": 4038,
      "on_time_orders": 4396,
      "in_full_orders": 10659,
      "otif_rate": 0.3293,
      "on_time_rate": 0.3585,
      "in_full_rate": 0.8692
    },
    {
      "month": "2023-11",
      "total_orders": 12019,
      "otif_orders": 3918,
      "on_time_orders": 4327,
      "in_full_orders": 10401,
      "otif_rate": 0.326,
      "on_time_rate": 0.36,
      "in_full_rate": 0.8654
    },
    {
      "month": "2023-12",
      "total_orders": 12384,
      "otif_orders": 4057,
      "on_time_orders": 4443,
      "in_full_orders": 10686,
      "otif_rate": 0.3276,
      "on_time_rate": 0.3588,
      "in_full_rate": 0.8629
    },
    {
      "month": "2024-01",
      "total_orders": 12175,
      "otif_orders": 3979,
      "on_time_orders": 4332,
      "in_full_orders": 10556,
      "otif_rate": 0.3268,
      "on_time_rate": 0.3558,
      "in_full_rate": 0.867
    },
    {
      "month": "2024-02",
      "total_orders": 11358,
      "otif_orders": 3707,
      "on_time_orders": 4118,
      "in_full_orders": 9814,
      "otif_rate": 0.3264,
      "on_time_rate": 0.3626,
      "in_full_rate": 0.8641
    },
    {
      "month": "2024-03",
      "total_orders": 12085,
      "otif_orders": 3782,
      "on_time_orders": 4158,
      "in_full_orders": 10375,
      "otif_rate": 0.3129,
      "on_time_rate": 0.3441,
      "in_full_rate": 0.8585
    },
    {
      "month": "2024-04",
      "total_orders": 11860,
      "otif_orders": 3830,
      "on_time_orders": 4203,
      "in_full_orders": 10276,
      "otif_rate": 0.3229,
      "on_time_rate": 0.3544,
      "in_full_rate": 0.8664
    },
    {
      "month": "2024-05",
      "total_orders": 12414,
      "otif_orders": 3986,
      "on_time_orders": 4363,
      "in_full_orders": 10811,
      "otif_rate": 0.3211,
      "on_time_rate": 0.3515,
      "in_full_rate": 0.8709
    },
    {
      "month": "2024-06",
      "total_orders": 12053,
      "otif_orders": 3998,
      "on_time_orders": 4363,
      "in_full_orders": 10443,
      "otif_rate": 0.3317,
      "on_time_rate": 0.362,
      "in_full_rate": 0.8664
    },
    {
      "month": "2024-07",
      "total_orders": 12252,
      "otif_orders": 3977,
      "on_time_orders": 4329,
      "in_full_orders": 10699,
      "otif_rate": 0.3246,
      "on_time_rate": 0.3533,
      "in_full_rate": 0.8732
    },
    {
      "month": "2024-08",
      "total_orders": 12305,
      "otif_orders": 4022,
      "on_time_orders": 4391,
      "in_full_orders": 10732,
      "otif_rate": 0.3269,
      "on_time_rate": 0.3568,
      "in_full_rate": 0.8722
    },
    {
      "month": "2024-09",
      "total_orders": 11794,
      "otif_orders": 3849,
      "on_time_orders": 4207,
      "in_full_orders": 10273,
      "otif_rate": 0.3264,
      "on_time_rate": 0.3567,
      "in_full_rate": 0.871
    },
    {
      "month": "2024-10",
      "total_orders": 12025,
      "otif_orders": 3945,
      "on_time_orders": 4332,
      "in_full_orders": 10450,
      "otif_rate": 0.3281,
      "on_time_rate": 0.3602,
      "in_full_rate": 0.869
    },
    {
      "month": "2024-11",
      "total_orders": 11862,
      "otif_orders": 3795,
      "on_time_orders": 4197,
      "in_full_orders": 10238,
      "otif_rate": 0.3199,
      "on_time_rate": 0.3538,
      "in_full_rate": 0.8631
    },
    {
      "month": "2024-12",
      "total_orders": 12096,
      "otif_orders": 3910,
      "on_time_orders": 4287,
      "in_full_orders": 10398,
      "otif_rate": 0.3232,
      "on_time_rate": 0.3544,
      "in_full_rate": 0.8596
    },
    {
      "month": "2025-01",
      "total_orders": 9866,
      "otif_orders": 3178,
      "on_time_orders": 3519,
      "in_full_orders": 8439,
      "otif_rate": 0.3221,
      "on_time_rate": 0.3567,
      "in_full_rate": 0.8554
    },
    {
      "month": "2025-02",
      "total_orders": 3193,
      "otif_orders": 1055,
      "on_time_orders": 1161,
      "in_full_orders": 2769,
      "otif_rate": 0.3304,
      "on_time_rate": 0.3636,
      "in_full_rate": 0.8672
    },
    {
      "month": "2025-03",
      "total_orders": 10,
      "otif_orders": 1,
      "on_time_orders": 1,
      "in_full_orders": 9,
      "otif_rate": 0.1,
      "on_time_rate": 0.1,
      "in_full_rate": 0.9
    }
  ]
}